setup.py
elysiandltools/__init__.py
elysiandltools/event_util.py
elysiandltools/logger.py
elysiandltools/metric_cal.py
elysiandltools/model_util.py
elysiandltools.egg-info/PKG-INFO
elysiandltools.egg-info/SOURCES.txt
elysiandltools.egg-info/dependency_links.txt
elysiandltools.egg-info/not-zip-safe
elysiandltools.egg-info/top_level.txt
elysiandltools/loss_function/__init__.py
elysiandltools/loss_function/loss_func.py